{
  "bff_meta": null,
  "error": null,
  "error_msg": null,
  "data": {
    "item": {
      "item_id": 9560535771,
      "shop_id": 158804442,
      "item_status": "normal",
      "status": 1,
      "item_type": 0,
      "reference_item_id": "",
      "title": "ERCO TIRE Ban Luar Motor Matic Depan Belakang Tubeless NonTubeless Ukuran 90/90-14 Dan 80/90-14",
      "image": "id-11134207-7rase-m59ofxfl4sjm44",
      "label_ids": [
        1001038,
        1011751,
        1011747,
        700020158,
        844931086908638,
        1400285055,
        1015914,
        700190087,
        298458335,
        298458334,
        1049116,
        700005557,
        822059908662278,
        1400066662,
        825465608497696,
        825465608499232,
        837860934119952,
        1002164,
        1000031,
        1718087960,
        1428713,
        1119699,
        1718093079,
        1000669,
        1400025118,
        825465608492064,
        1213641,
        700610210,
        700610229,
        998056015,
        1718093085,
        700585042,
        1718093084,
        298458396
      ],
      "is_adult": false,
      "is_preview": false,
      "flag": 65536,
      "is_service_by_shopee": false,
      "condition": 1,
      "cat_id": 100641,
      "has_low_fulfillment_rate": false,
      "is_live_streaming_price": null,
      "currency": "IDR",
      "brand": "Erco",
      "brand_id": 1957770,
      "show_discount": 0,
      "ctime": 1622257996,
      "item_rating": {
        "rating_star": 4.577985323549033
      },
      "cb_option": 0,
      "has_model_with_available_shopee_stock": false,
      "shop_location": "KAB. BANYUWANGI",
      "attributes": [
        {
          "name": "Bahan",
          "value": "Alloy, Double Nylon",
          "id": 100134,
          "is_timestamp": false,
          "brand_option": null,
          "val_id": 1629,
          "url": null,
          "brand_id": null,
          "full_url": null,
          "type": null
        },
        {
          "name": "Set Bundle",
          "value": "Ya",
          "id": 100391,
          "is_timestamp": false,
          "brand_option": null,
          "val_id": 2495,
          "url": null,
          "brand_id": null,
          "full_url": null,
          "type": null
        },
        {
          "name": "Jenis Ban",
          "value": "Performance Semua Musim",
          "id": 100880,
          "is_timestamp": false,
          "brand_option": null,
          "val_id": 4675,
          "url": null,
          "brand_id": null,
          "full_url": null,
          "type": null
        },
        {
          "name": "Masa Garansi",
          "value": "1 Bulan",
          "id": 100121,
          "is_timestamp": false,
          "brand_option": null,
          "val_id": 776,
          "url": null,
          "brand_id": null,
          "full_url": null,
          "type": null
        },
        {
          "name": "Jenis Garansi",
          "value": "Garansi Produsen",
          "id": 100370,
          "is_timestamp": false,
          "brand_option": null,
          "val_id": 2419,
          "url": null,
          "brand_id": null,
          "full_url": null,
          "type": null
        },
        {
          "name": "Ukuran Ban Sepeda Motor",
          "value": "90/90-14",
          "id": 100917,
          "is_timestamp": false,
          "brand_option": null,
          "val_id": 0,
          "url": null,
          "brand_id": null,
          "full_url": null,
          "type": null
        },
        {
          "name": "No.Sertifikat (SNI,K3L,UTTP)",
          "value": "31052200380910001",
          "id": 101256,
          "is_timestamp": false,
          "brand_option": null,
          "val_id": 0,
          "url": null,
          "brand_id": null,
          "full_url": null,
          "type": null
        }
      ],
      "rich_text_description": null,
      "invoice_option": null,
      "is_category_failed": null,
      "is_prescription_item": false,
      "preview_info": null,
      "show_prescription_feed": false,
      "is_alcohol_product": false,
      "is_infant_milk_formula_product": false,
      "is_unavailable": false,
      "is_partial_fulfilled": false,
      "is_presale": false,
      "is_presale_deposit_item": null,
      "is_presale_deposit_made": null,
      "description": "ERCO Official Store adalah akun resmi dari ERCO di platform shopee\nWaktu Operasional : Senin - Sabtu jam 07.00 - 16.00\nBan ERCO Merupan Ban Vulkanisir atau ban daur ulang\nuntuk keamanan dan kualitas sudah pasti terjamin dan pastinya aman digunakan saat berkendara, untuk jarak tempuh yang jauh sangat di rekomendasikan memilih ban merek ERCO dari pada merek yang lain, garansi 1 bulan apabila ban mengalami kembung\nNOTE : Pemesanan diatas jam 15.00 WIB akan di ikutkan pengiriman di keesokan harinya ya\nHarga Diatas Merupakan Harga Satuan Per Biji Ya\nUntuk ukuran 90/90-14  itu untuk ban motor belakang matic\nUntuk ukuran 80/90-14 itu untuk ban motor depan matic\nType Tubeless Tanpa Menggunakan Ban dalam\nType NonTubeless Memakai Ban Dalam\nBisa di aplikasikan di motor motor matic ring 14\nHonda: \nVario Karbu\nVario 125\nVario FI\nBeat Karbu\nBeat FI\nBeat Street\nScoppy Tahun 2012-2015\nGenio 2017-2022\nYamaha :\nGear 125\nX-Ride 125\nMio M3\nFino 125\nMio Old\nMio Soul\nMio GT\nTerimakasih Selamat Belanja\nCATATAN :\nuntuk kategori variasi BS adalah ban yang reject produksi atau ban erco yang tidak masuk standart quality proses jadi harganya pasti lebih murah, untuk ban BS matic disarankan tidak digunakan untuk tubeless, kita sarankan menggunakan ban dalam, ban BS mereknya dihapus dan dikirim tanpa bungkus\nJika ingin membeli 1 set , silahkan check out 2x Sesuai pilihan variasi ",
      "categories": [
        {
          "catid": 100641,
          "display_name": "Sepeda Motor",
          "no_sub": false,
          "is_default_subcat": false
        },
        {
          "catid": 100757,
          "display_name": "Suku Cadang Motor",
          "no_sub": false,
          "is_default_subcat": false
        },
        {
          "catid": 101495,
          "display_name": "Ban Motor & Aksesoris",
          "no_sub": true,
          "is_default_subcat": false
        }
      ],
      "fe_categories": [
        {
          "catid": 11043660,
          "display_name": "Otomotif",
          "no_sub": false,
          "is_default_subcat": false
        },
        {
          "catid": 11043747,
          "display_name": "Suku Cadang Motor",
          "no_sub": false,
          "is_default_subcat": false
        },
        {
          "catid": 11043767,
          "display_name": "Ban Motor & Aksesoris",
          "no_sub": true,
          "is_default_subcat": false
        }
      ],
      "item_has_video": true,
      "presale_dday_start_time": null,
      "is_lowest_price_at_shopee": null,
      "display_description_disclosure_rsku_redirection": null,
      "models": [
        {
          "item_id": 9560535771,
          "status": 1,
          "current_promotion_reserved_stock": 0,
          "name": "Satu Set Matic,Tubeless",
          "promotion_id": 567073365835776,
          "price": 30357200000,
          "price_stocks": [
            {
              "allocated_stock": null,
              "stock_breakdown_by_location": null,
              "promotion_type": 301
            },
            {
              "allocated_stock": 0,
              "stock_breakdown_by_location": [
                {
                  "location_id": "IDZ",
                  "available_stock": 0,
                  "fulfilment_type": 2,
                  "address_id": 0,
                  "allocated_stock": null
                }
              ],
              "promotion_type": 0
            }
          ],
          "current_promotion_has_reserve_stock": false,
          "normal_stock": 0,
          "extinfo": {
            "tier_index": [
              2,
              0
            ],
            "is_pre_order": false,
            "estimated_days": 2
          },
          "price_before_discount": 60714300000,
          "model_id": 109269862555,
          "stock": 0,
          "has_gimmick_tag": false,
          "key_measurement": null,
          "sold": 1105,
          "is_lowest_price_at_shopee": false
        },
        {
          "item_id": 9560535771,
          "status": 1,
          "current_promotion_reserved_stock": 0,
          "name": "80/90-14,NonTubeless",
          "promotion_id": 567073365835776,
          "price": 12500000000,
          "price_stocks": [
            {
              "allocated_stock": null,
              "stock_breakdown_by_location": null,
              "promotion_type": 301
            },
            {
              "allocated_stock": 0,
              "stock_breakdown_by_location": [
                {
                  "location_id": "IDZ",
                  "available_stock": 19317,
                  "fulfilment_type": 2,
                  "address_id": 0,
                  "allocated_stock": null
                }
              ],
              "promotion_type": 0
            }
          ],
          "current_promotion_has_reserve_stock": false,
          "normal_stock": 19317,
          "extinfo": {
            "tier_index": [
              0,
              1
            ],
            "is_pre_order": false,
            "estimated_days": 2
          },
          "price_before_discount": 25000000000,
          "model_id": 49427525264,
          "stock": 19317,
          "has_gimmick_tag": false,
          "key_measurement": null,
          "sold": 952,
          "is_lowest_price_at_shopee": false
        },
        {
          "item_id": 9560535771,
          "status": 1,
          "current_promotion_reserved_stock": 0,
          "name": "90/90-14,NonTubeless",
          "promotion_id": 567073365835776,
          "price": 14285700000,
          "price_stocks": [
            {
              "allocated_stock": null,
              "stock_breakdown_by_location": null,
              "promotion_type": 301
            },
            {
              "allocated_stock": 0,
              "stock_breakdown_by_location": [
                {
                  "location_id": "IDZ",
                  "available_stock": 31,
                  "fulfilment_type": 2,
                  "address_id": 0,
                  "allocated_stock": null
                }
              ],
              "promotion_type": 0
            }
          ],
          "current_promotion_has_reserve_stock": false,
          "normal_stock": 31,
          "extinfo": {
            "tier_index": [
              1,
              1
            ],
            "is_pre_order": false,
            "estimated_days": 2
          },
          "price_before_discount": 28571400000,
          "model_id": 59777195752,
          "stock": 31,
          "has_gimmick_tag": false,
          "key_measurement": null,
          "sold": 1428,
          "is_lowest_price_at_shopee": false
        },
        {
          "item_id": 9560535771,
          "status": 1,
          "current_promotion_reserved_stock": 0,
          "name": "Satu Set Matic,BS/Sortir NonBungkus",
          "promotion_id": 567073365835776,
          "price": 18849200000,
          "price_stocks": [
            {
              "allocated_stock": null,
              "stock_breakdown_by_location": null,
              "promotion_type": 301
            },
            {
              "allocated_stock": 0,
              "stock_breakdown_by_location": [
                {
                  "location_id": "IDZ",
                  "available_stock": 1,
                  "fulfilment_type": 2,
                  "address_id": 0,
                  "allocated_stock": null
                }
              ],
              "promotion_type": 0
            }
          ],
          "current_promotion_has_reserve_stock": false,
          "normal_stock": 1,
          "extinfo": {
            "tier_index": [
              2,
              2
            ],
            "is_pre_order": false,
            "estimated_days": 2
          },
          "price_before_discount": 37698400000,
          "model_id": 109269862557,
          "stock": 1,
          "has_gimmick_tag": false,
          "key_measurement": null,
          "sold": 25,
          "is_lowest_price_at_shopee": false
        },
        {
          "item_id": 9560535771,
          "status": 1,
          "current_promotion_reserved_stock": 0,
          "name": "Satu Set Matic,NonTubeless",
          "promotion_id": 567073365835776,
          "price": 26785700000,
          "price_stocks": [
            {
              "allocated_stock": null,
              "stock_breakdown_by_location": null,
              "promotion_type": 301
            },
            {
              "allocated_stock": 0,
              "stock_breakdown_by_location": [
                {
                  "location_id": "IDZ",
                  "available_stock": 31,
                  "fulfilment_type": 2,
                  "address_id": 0,
                  "allocated_stock": null
                }
              ],
              "promotion_type": 0
            }
          ],
          "current_promotion_has_reserve_stock": false,
          "normal_stock": 31,
          "extinfo": {
            "tier_index": [
              2,
              1
            ],
            "is_pre_order": false,
            "estimated_days": 2
          },
          "price_before_discount": 53571400000,
          "model_id": 109269862556,
          "stock": 31,
          "has_gimmick_tag": false,
          "key_measurement": null,
          "sold": 283,
          "is_lowest_price_at_shopee": false
        },
        {
          "item_id": 9560535771,
          "status": 1,
          "current_promotion_reserved_stock": 0,
          "name": "90/90-14,BS/Sortir NonBungkus",
          "promotion_id": 567073365835776,
          "price": 9920700000,
          "price_stocks": [
            {
              "allocated_stock": null,
              "stock_breakdown_by_location": null,
              "promotion_type": 301
            },
            {
              "allocated_stock": 0,
              "stock_breakdown_by_location": [
                {
                  "location_id": "IDZ",
                  "available_stock": 1,
                  "fulfilment_type": 2,
                  "address_id": 0,
                  "allocated_stock": null
                }
              ],
              "promotion_type": 0
            }
          ],
          "current_promotion_has_reserve_stock": false,
          "normal_stock": 1,
          "extinfo": {
            "tier_index": [
              1,
              2
            ],
            "is_pre_order": false,
            "estimated_days": 2
          },
          "price_before_discount": 19841300000,
          "model_id": 59777195754,
          "stock": 1,
          "has_gimmick_tag": false,
          "key_measurement": null,
          "sold": 157,
          "is_lowest_price_at_shopee": false
        },
        {
          "item_id": 9560535771,
          "status": 1,
          "current_promotion_reserved_stock": 0,
          "name": "80/90-14,BS/Sortir NonBungkus",
          "promotion_id": 567073365835776,
          "price": 8928600000,
          "price_stocks": [
            {
              "allocated_stock": null,
              "stock_breakdown_by_location": null,
              "promotion_type": 301
            },
            {
              "allocated_stock": 0,
              "stock_breakdown_by_location": [
                {
                  "location_id": "IDZ",
                  "available_stock": 1,
                  "fulfilment_type": 2,
                  "address_id": 0,
                  "allocated_stock": null
                }
              ],
              "promotion_type": 0
            }
          ],
          "current_promotion_has_reserve_stock": false,
          "normal_stock": 1,
          "extinfo": {
            "tier_index": [
              0,
              2
            ],
            "is_pre_order": false,
            "estimated_days": 2
          },
          "price_before_discount": 17857100000,
          "model_id": 59777195748,
          "stock": 1,
          "has_gimmick_tag": false,
          "key_measurement": null,
          "sold": 105,
          "is_lowest_price_at_shopee": false
        },
        {
          "item_id": 9560535771,
          "status": 1,
          "current_promotion_reserved_stock": 0,
          "name": "90/90-14,Tubeless",
          "promotion_id": 567073365835776,
          "price": 16071500000,
          "price_stocks": [
            {
              "allocated_stock": null,
              "stock_breakdown_by_location": null,
              "promotion_type": 301
            },
            {
              "allocated_stock": 0,
              "stock_breakdown_by_location": [
                {
                  "location_id": "IDZ",
                  "available_stock": 3034,
                  "fulfilment_type": 2,
                  "address_id": 0,
                  "allocated_stock": null
                }
              ],
              "promotion_type": 0
            }
          ],
          "current_promotion_has_reserve_stock": false,
          "normal_stock": 3034,
          "extinfo": {
            "tier_index": [
              1,
              0
            ],
            "is_pre_order": false,
            "estimated_days": 2
          },
          "price_before_discount": 32142900000,
          "model_id": 59777195749,
          "stock": 3034,
          "has_gimmick_tag": false,
          "key_measurement": null,
          "sold": 4519,
          "is_lowest_price_at_shopee": false
        },
        {
          "item_id": 9560535771,
          "status": 1,
          "current_promotion_reserved_stock": 0,
          "name": "80/90-14,Tubeless",
          "promotion_id": 567073365835776,
          "price": 14285700000,
          "price_stocks": [
            {
              "allocated_stock": null,
              "stock_breakdown_by_location": null,
              "promotion_type": 301
            },
            {
              "allocated_stock": 0,
              "stock_breakdown_by_location": [
                {
                  "location_id": "IDZ",
                  "available_stock": 0,
                  "fulfilment_type": 2,
                  "address_id": 0,
                  "allocated_stock": null
                }
              ],
              "promotion_type": 0
            }
          ],
          "current_promotion_has_reserve_stock": false,
          "normal_stock": 0,
          "extinfo": {
            "tier_index": [
              0,
              0
            ],
            "is_pre_order": false,
            "estimated_days": 2
          },
          "price_before_discount": 28571400000,
          "model_id": 49427525261,
          "stock": 0,
          "has_gimmick_tag": false,
          "key_measurement": null,
          "sold": 3192,
          "is_lowest_price_at_shopee": false
        }
      ],
      "tier_variations": [
        {
          "name": "Ukuran",
          "options": [
            "80/90-14",
            "90/90-14",
            "Satu Set Matic"
          ],
          "images": [
            "id-11134207-7rasl-m59ofxfl66xkad",
            "id-11134207-7rasf-m59ofxfl7li048",
            "id-11134207-7rash-m59ofxfl902gca"
          ],
          "properties": null,
          "type": 0,
          "summed_stocks": null,
          "display_indicators": [
            0,
            0,
            0
          ]
        },
        {
          "name": "Type",
          "options": [
            "Tubeless",
            "NonTubeless",
            "BS/Sortir NonBungkus"
          ],
          "images": null,
          "properties": null,
          "type": 0,
          "summed_stocks": null,
          "display_indicators": [
            0,
            0,
            0
          ]
        }
      ],
      "size_chart": null,
      "size_chart_info": null,
      "welcome_package_type": 0,
      "is_free_gift": false,
      "deep_discount": null,
      "is_low_price_eligible": null,
      "bundle_deal_info": null,
      "add_on_deal_info": null,
      "shipping_icon_type": 0,
      "badge_icon_type": 0,
      "spl_info": {
        "installment_info": null,
        "user_credit_info": null,
        "channel_id": null,
        "show_spl": true,
        "show_spl_lite": null,
        "spl_xtra": null,
        "spl_motorcycle_loan": null
      },
      "estimated_days": 2,
      "is_pre_order": false,
      "is_free_shipping": false,
      "overall_purchase_limit": null,
      "min_purchase_limit": 0,
      "is_hide_stock": false,
      "stock": 22416,
      "normal_stock": 22416,
      "current_promotion_reserved_stock": 0,
      "can_use_wholesale": false,
      "wholesale_tier_list": [],
      "price": 8928600000,
      "raw_discount": 0,
      "hidden_price_display": null,
      "price_min": 8928600000,
      "price_max": 26785700000,
      "price_before_discount": 17857100000,
      "price_min_before_discount": 17857100000,
      "price_max_before_discount": 53571400000,
      "other_stock": 0,
      "discount_stock": 22416,
      "current_promotion_has_reserve_stock": false,
      "complaint_policy": null,
      "show_recycling_info": null,
      "should_show_amp_tag": true,
      "all_models_has_pre_order": false,
      "is_item_inherited": false,
      "max_quantity": 22416
    },
    "account": {
      "user_id": 264211770,
      "is_new_user": false,
      "default_address": {
        "state": "JAWA BARAT",
        "city": "KOTA BANDUNG",
        "district": "BABAKAN CIPARAY",
        "town": "",
        "zip_code": "40223",
        "address": null,
        "region": null,
        "longitude": null,
        "latitude": null
      },
      "adult_consent": 0,
      "birth_timestamp": 1142528400
    },
    "product_images": {
      "video": {
        "video_id": "api/v4/11110105/mms/id-11110105-6ke1n-lyyvis0oge08ab.16000081723710992.mp4",
        "thumb_url": "id-11110105-7r98s-lyyvj6zsjsrre4",
        "duration": 17,
        "version": 2,
        "vid": "id-11110105-6ke1n-lyyvis0oge08ab",
        "formats": [
          {
            "format": 1600322,
            "defn": "V360P",
            "profile": "MP4",
            "path": "api/v4/11110105/mms/id-11110105-6ke1n-lyyvis0oge08ab.16003221724153945.mp4",
            "url": "https://down-aka-sg.vod.susercontent.com/api/v4/11110105/mms/id-11110105-6ke1n-lyyvis0oge08ab.16003221724153945.mp4",
            "width": 360,
            "height": 640
          },
          {
            "format": 1600408,
            "defn": "V360P",
            "profile": "MP4",
            "path": "api/v4/11110105/mms/id-11110105-6ke1n-lyyvis0oge08ab.16004081724160007.mp4",
            "url": "https://down-aka-sg.vod.susercontent.com/api/v4/11110105/mms/id-11110105-6ke1n-lyyvis0oge08ab.16004081724160007.mp4",
            "width": 360,
            "height": 640
          },
          {
            "format": 1600673,
            "defn": "V540P",
            "profile": "MP4",
            "path": "api/v4/11110105/mms/id-11110105-6ke1n-lyyvis0oge08ab.16006731728437647.mp4",
            "url": "https://down-aka-sg.vod.susercontent.com/api/v4/11110105/mms/id-11110105-6ke1n-lyyvis0oge08ab.16006731728437647.mp4",
            "width": 540,
            "height": 960
          },
          {
            "format": 1600671,
            "defn": "V540P",
            "profile": "MP4",
            "path": "api/v4/11110105/mms/id-11110105-6ke1n-lyyvis0oge08ab.16006711724153945.mp4",
            "url": "https://down-aka-sg.vod.susercontent.com/api/v4/11110105/mms/id-11110105-6ke1n-lyyvis0oge08ab.16006711724153945.mp4",
            "width": 540,
            "height": 960
          },
          {
            "format": 1600266,
            "defn": "V540P",
            "profile": "MP4",
            "path": "api/v4/11110105/mms/id-11110105-6ke1n-lyyvis0oge08ab.16002661724151921.mp4",
            "url": "https://down-aka-sg.vod.susercontent.com/api/v4/11110105/mms/id-11110105-6ke1n-lyyvis0oge08ab.16002661724151921.mp4",
            "width": 540,
            "height": 960
          },
          {
            "format": 1600265,
            "defn": "V540P",
            "profile": "MP4",
            "path": "api/v4/11110105/mms/id-11110105-6ke1n-lyyvis0oge08ab.16002651724151910.mp4",
            "url": "https://down-aka-sg.vod.susercontent.com/api/v4/11110105/mms/id-11110105-6ke1n-lyyvis0oge08ab.16002651724151910.mp4",
            "width": 540,
            "height": 960
          },
          {
            "format": 1600409,
            "defn": "V540P",
            "profile": "MP4",
            "path": "api/v4/11110105/mms/id-11110105-6ke1n-lyyvis0oge08ab.16004091724160007.mp4",
            "url": "https://down-aka-sg.vod.susercontent.com/api/v4/11110105/mms/id-11110105-6ke1n-lyyvis0oge08ab.16004091724160007.mp4",
            "width": 540,
            "height": 960
          },
          {
            "format": 1600659,
            "defn": "V540P",
            "profile": "MP4",
            "path": "api/v4/11110105/mms/id-11110105-6ke1n-lyyvis0oge08ab.16006591724160007.mp4",
            "url": "https://down-aka-sg.vod.susercontent.com/api/v4/11110105/mms/id-11110105-6ke1n-lyyvis0oge08ab.16006591724160007.mp4",
            "width": 540,
            "height": 960
          },
          {
            "format": 1600008,
            "defn": "V720P",
            "profile": "MP4",
            "path": "api/v4/11110105/mms/id-11110105-6ke1n-lyyvis0oge08ab.16000081723710992.mp4",
            "url": "https://down-aka-sg.vod.susercontent.com/api/v4/11110105/mms/id-11110105-6ke1n-lyyvis0oge08ab.16000081723710992.mp4",
            "width": 720,
            "height": 1280
          },
          {
            "format": 1600324,
            "defn": "V720P",
            "profile": "MP4",
            "path": "api/v4/11110105/mms/id-11110105-6ke1n-lyyvis0oge08ab.16003241724153945.mp4",
            "url": "https://down-aka-sg.vod.susercontent.com/api/v4/11110105/mms/id-11110105-6ke1n-lyyvis0oge08ab.16003241724153945.mp4",
            "width": 720,
            "height": 1280
          },
          {
            "format": 1600325,
            "defn": "V720P",
            "profile": "MP4",
            "path": "api/v4/11110105/mms/id-11110105-6ke1n-lyyvis0oge08ab.16003251724153945.mp4",
            "url": "https://down-aka-sg.vod.susercontent.com/api/v4/11110105/mms/id-11110105-6ke1n-lyyvis0oge08ab.16003251724153945.mp4",
            "width": 720,
            "height": 1280
          },
          {
            "format": 1600267,
            "defn": "V720P",
            "profile": "MP4",
            "path": "api/v4/11110105/mms/id-11110105-6ke1n-lyyvis0oge08ab.16002671724151921.mp4",
            "url": "https://down-aka-sg.vod.susercontent.com/api/v4/11110105/mms/id-11110105-6ke1n-lyyvis0oge08ab.16002671724151921.mp4",
            "width": 720,
            "height": 1280
          },
          {
            "format": 1600410,
            "defn": "V720P",
            "profile": "MP4",
            "path": "api/v4/11110105/mms/id-11110105-6ke1n-lyyvis0oge08ab.16004101724160007.mp4",
            "url": "https://down-aka-sg.vod.susercontent.com/api/v4/11110105/mms/id-11110105-6ke1n-lyyvis0oge08ab.16004101724160007.mp4",
            "width": 720,
            "height": 1280
          },
          {
            "format": 1600411,
            "defn": "V720P",
            "profile": "MP4",
            "path": "api/v4/11110105/mms/id-11110105-6ke1n-lyyvis0oge08ab.16004111724160007.mp4",
            "url": "https://down-aka-sg.vod.susercontent.com/api/v4/11110105/mms/id-11110105-6ke1n-lyyvis0oge08ab.16004111724160007.mp4",
            "width": 720,
            "height": 1280
          }
        ],
        "default_format": {
          "format": 1600323,
          "defn": "V540P",
          "profile": "MP4",
          "path": "",
          "url": "https://mms.vod.susercontent.com/api/v4/11110105/mms/id-11110105-6ke1n-lyyvis0oge08ab.default.mp4",
          "width": 540,
          "height": 960
        },
        "mms_data": "{\"vid\":\"id-11110105-6ke1n-lyyvis0oge08ab\",\"biz\":107,\"duration\":17322,\"create_time\":1723710989,\"update_time\":1723710995,\"serviceID\":2,\"cover\":\"https://down-aka-sg.img.susercontent.com/id-11110105-7r98s-lyyvj6zsjsrre4\",\"formats\":[{\"format\":1600322,\"defn\":\"V360P\",\"profile\":\"MP4\",\"path\":\"api/v4/11110105/mms/id-11110105-6ke1n-lyyvis0oge08ab.16003221724153945.mp4\",\"url\":\"https://down-aka-sg.vod.susercontent.com/api/v4/11110105/mms/id-11110105-6ke1n-lyyvis0oge08ab.16003221724153945.mp4\",\"width\":360,\"height\":640,\"bitrate\":223069,\"abitrate\":96426,\"duration\":17024,\"size\":693581,\"fps\":25.05882,\"update_time\":1724153950,\"codec\":\"H264\"},{\"format\":1600408,\"defn\":\"V360P\",\"profile\":\"MP4\",\"path\":\"api/v4/11110105/mms/id-11110105-6ke1n-lyyvis0oge08ab.16004081724160007.mp4\",\"url\":\"https://down-aka-sg.vod.susercontent.com/api/v4/11110105/mms/id-11110105-6ke1n-lyyvis0oge08ab.16004081724160007.mp4\",\"width\":360,\"height\":640,\"bitrate\":240036,\"abitrate\":96400,\"duration\":17020,\"size\":730794,\"fps\":25.05882,\"update_time\":1724160012,\"codec\":\"H264\"},{\"format\":1600673,\"defn\":\"V540P\",\"profile\":\"MP4\",\"path\":\"api/v4/11110105/mms/id-11110105-6ke1n-lyyvis0oge08ab.16006731728437647.mp4\",\"url\":\"https://down-aka-sg.vod.susercontent.com/api/v4/11110105/mms/id-11110105-6ke1n-lyyvis0oge08ab.16006731728437647.mp4\",\"width\":540,\"height\":960,\"bitrate\":998470,\"abitrate\":64469,\"duration\":17040,\"size\":2279454,\"fps\":25,\"update_time\":1728437656,\"codec\":\"H264\"},{\"format\":1600671,\"defn\":\"V540P\",\"profile\":\"MP4\",\"path\":\"api/v4/11110105/mms/id-11110105-6ke1n-lyyvis0oge08ab.16006711724153945.mp4\",\"url\":\"https://down-aka-sg.vod.susercontent.com/api/v4/11110105/mms/id-11110105-6ke1n-lyyvis0oge08ab.16006711724153945.mp4\",\"width\":540,\"height\":960,\"bitrate\":535928,\"abitrate\":64469,\"duration\":17020,\"size\":1291567,\"fps\":25.05882,\"update_time\":1724153955,\"codec\":\"H264\"},{\"format\":1600266,\"defn\":\"V540P\",\"profile\":\"MP4\",\"path\":\"api/v4/11110105/mms/id-11110105-6ke1n-lyyvis0oge08ab.16002661724151921.mp4\",\"url\":\"https://down-aka-sg.vod.susercontent.com/api/v4/11110105/mms/id-11110105-6ke1n-lyyvis0oge08ab.16002661724151921.mp4\",\"width\":540,\"height\":960,\"bitrate\":540471,\"abitrate\":64469,\"duration\":17020,\"size\":1301221,\"fps\":25.05882,\"update_time\":1724151932,\"codec\":\"H264\"},{\"format\":1600265,\"defn\":\"V540P\",\"profile\":\"MP4\",\"path\":\"api/v4/11110105/mms/id-11110105-6ke1n-lyyvis0oge08ab.16002651724151910.mp4\",\"url\":\"https://down-aka-sg.vod.susercontent.com/api/v4/11110105/mms/id-11110105-6ke1n-lyyvis0oge08ab.16002651724151910.mp4\",\"width\":540,\"height\":960,\"bitrate\":1026744,\"abitrate\":64469,\"duration\":17020,\"size\":2334551,\"fps\":25.05882,\"update_time\":1724151921,\"codec\":\"H264\"},{\"format\":1600409,\"defn\":\"V540P\",\"profile\":\"MP4\",\"path\":\"api/v4/11110105/mms/id-11110105-6ke1n-lyyvis0oge08ab.16004091724160007.mp4\",\"url\":\"https://down-aka-sg.vod.susercontent.com/api/v4/11110105/mms/id-11110105-6ke1n-lyyvis0oge08ab.16004091724160007.mp4\",\"width\":540,\"height\":960,\"bitrate\":570528,\"abitrate\":64469,\"duration\":17020,\"size\":1365061,\"fps\":25.05882,\"update_time\":1724160018,\"codec\":\"H264\"},{\"format\":1600659,\"defn\":\"V540P\",\"profile\":\"MP4\",\"path\":\"api/v4/11110105/mms/id-11110105-6ke1n-lyyvis0oge08ab.16006591724160007.mp4\",\"url\":\"https://down-aka-sg.vod.susercontent.com/api/v4/11110105/mms/id-11110105-6ke1n-lyyvis0oge08ab.16006591724160007.mp4\",\"width\":540,\"height\":960,\"bitrate\":1072868,\"abitrate\":64469,\"duration\":17020,\"size\":2432532,\"fps\":25.05882,\"update_time\":1724160018,\"codec\":\"H264\"},{\"format\":1600008,\"defn\":\"V720P\",\"profile\":\"MP4\",\"path\":\"api/v4/11110105/mms/id-11110105-6ke1n-lyyvis0oge08ab.16000081723710992.mp4\",\"url\":\"https://down-aka-sg.vod.susercontent.com/api/v4/11110105/mms/id-11110105-6ke1n-lyyvis0oge08ab.16000081723710992.mp4\",\"width\":720,\"height\":1280,\"bitrate\":1146155,\"abitrate\":127319,\"duration\":17020,\"size\":2722092,\"fps\":25.05882,\"update_time\":1723711008,\"codec\":\"H264\"},{\"format\":1600324,\"defn\":\"V720P\",\"profile\":\"MP4\",\"path\":\"api/v4/11110105/mms/id-11110105-6ke1n-lyyvis0oge08ab.16003241724153945.mp4\",\"url\":\"https://down-aka-sg.vod.susercontent.com/api/v4/11110105/mms/id-11110105-6ke1n-lyyvis0oge08ab.16003241724153945.mp4\",\"width\":720,\"height\":1280,\"bitrate\":802688,\"abitrate\":127373,\"duration\":17024,\"size\":1999565,\"fps\":30.05882,\"update_time\":1724153964,\"codec\":\"H264\"},{\"format\":1600325,\"defn\":\"V720P\",\"profile\":\"MP4\",\"path\":\"api/v4/11110105/mms/id-11110105-6ke1n-lyyvis0oge08ab.16003251724153945.mp4\",\"url\":\"https://down-aka-sg.vod.susercontent.com/api/v4/11110105/mms/id-11110105-6ke1n-lyyvis0oge08ab.16003251724153945.mp4\",\"width\":720,\"height\":1280,\"bitrate\":1485393,\"abitrate\":127373,\"duration\":17024,\"size\":3450312,\"fps\":30.05882,\"update_time\":1724153976,\"codec\":\"H264\"},{\"format\":1600267,\"defn\":\"V720P\",\"profile\":\"MP4\",\"path\":\"api/v4/11110105/mms/id-11110105-6ke1n-lyyvis0oge08ab.16002671724151921.mp4\",\"url\":\"https://down-aka-sg.vod.susercontent.com/api/v4/11110105/mms/id-11110105-6ke1n-lyyvis0oge08ab.16002671724151921.mp4\",\"width\":720,\"height\":1280,\"bitrate\":1484170,\"abitrate\":127319,\"duration\":17020,\"size\":3447242,\"fps\":30.05882,\"update_time\":1724151942,\"codec\":\"H264\"},{\"format\":1600410,\"defn\":\"V720P\",\"profile\":\"MP4\",\"path\":\"api/v4/11110105/mms/id-11110105-6ke1n-lyyvis0oge08ab.16004101724160007.mp4\",\"url\":\"https://down-aka-sg.vod.susercontent.com/api/v4/11110105/mms/id-11110105-6ke1n-lyyvis0oge08ab.16004101724160007.mp4\",\"width\":720,\"height\":1280,\"bitrate\":795630,\"abitrate\":127319,\"duration\":17020,\"size\":1977114,\"fps\":25.05882,\"update_time\":1724160024,\"codec\":\"H264\"},{\"format\":1600411,\"defn\":\"V720P\",\"profile\":\"MP4\",\"path\":\"api/v4/11110105/mms/id-11110105-6ke1n-lyyvis0oge08ab.16004111724160007.mp4\",\"url\":\"https://down-aka-sg.vod.susercontent.com/api/v4/11110105/mms/id-11110105-6ke1n-lyyvis0oge08ab.16004111724160007.mp4\",\"width\":720,\"height\":1280,\"bitrate\":1617081,\"abitrate\":127319,\"duration\":17020,\"size\":3729695,\"fps\":30.05882,\"update_time\":1724160024,\"codec\":\"H264\"}],\"extend_formats\":{\"H265\":[{\"format\":1600315,\"defn\":\"V360P\",\"profile\":\"MP4\",\"path\":\"api/v4/11110105/mms/id-11110105-6ke1n-lyyvis0oge08ab.16003151724153928.mp4\",\"url\":\"https://down-aka-sg.vod.susercontent.com/api/v4/11110105/mms/id-11110105-6ke1n-lyyvis0oge08ab.16003151724153928.mp4\",\"width\":360,\"height\":640,\"bitrate\":276690,\"abitrate\":96400,\"duration\":17020,\"size\":811464,\"fps\":25.05882,\"update_time\":1724153944,\"codec\":\"H265\"},{\"format\":1600412,\"defn\":\"V360P\",\"profile\":\"MP4\",\"path\":\"api/v4/11110105/mms/id-11110105-6ke1n-lyyvis0oge08ab.16004121724159994.mp4\",\"url\":\"https://down-aka-sg.vod.susercontent.com/api/v4/11110105/mms/id-11110105-6ke1n-lyyvis0oge08ab.16004121724159994.mp4\",\"width\":360,\"height\":640,\"bitrate\":204212,\"abitrate\":96400,\"duration\":17020,\"size\":657448,\"fps\":25.05882,\"update_time\":1724160006,\"codec\":\"H265\"},{\"format\":1600246,\"defn\":\"V360P\",\"profile\":\"MP4\",\"path\":\"api/v4/11110105/mms/id-11110105-6ke1n-lyyvis0oge08ab.16002461727681285.mp4\",\"url\":\"https://down-aka-sg.vod.susercontent.com/api/v4/11110105/mms/id-11110105-6ke1n-lyyvis0oge08ab.16002461727681285.mp4\",\"width\":360,\"height\":640,\"bitrate\":202986,\"abitrate\":32338,\"duration\":17040,\"size\":516276,\"fps\":25,\"update_time\":1727681298,\"codec\":\"H265\"},{\"format\":1600307,\"defn\":\"V540P\",\"profile\":\"MP4\",\"path\":\"api/v4/11110105/mms/id-11110105-6ke1n-lyyvis0oge08ab.16003071724231787.mp4\",\"url\":\"https://down-aka-sg.vod.susercontent.com/api/v4/11110105/mms/id-11110105-6ke1n-lyyvis0oge08ab.16003071724231787.mp4\",\"width\":540,\"height\":960,\"bitrate\":444485,\"abitrate\":127319,\"duration\":17020,\"size\":1233826,\"fps\":25.05882,\"update_time\":1724231819,\"codec\":\"H265\"},{\"format\":1600316,\"defn\":\"V540P\",\"profile\":\"MP4\",\"path\":\"api/v4/11110105/mms/id-11110105-6ke1n-lyyvis0oge08ab.16003161724153945.mp4\",\"url\":\"https://down-aka-sg.vod.susercontent.com/api/v4/11110105/mms/id-11110105-6ke1n-lyyvis0oge08ab.16003161724153945.mp4\",\"width\":540,\"height\":960,\"bitrate\":464547,\"abitrate\":127319,\"duration\":17020,\"size\":1276441,\"fps\":25.05882,\"update_time\":1724153964,\"codec\":\"H265\"},{\"format\":1600413,\"defn\":\"V540P\",\"profile\":\"MP4\",\"path\":\"api/v4/11110105/mms/id-11110105-6ke1n-lyyvis0oge08ab.16004131724160007.mp4\",\"url\":\"https://down-aka-sg.vod.susercontent.com/api/v4/11110105/mms/id-11110105-6ke1n-lyyvis0oge08ab.16004131724160007.mp4\",\"width\":540,\"height\":960,\"bitrate\":366889,\"abitrate\":127319,\"duration\":17020,\"size\":1068919,\"fps\":25.05882,\"update_time\":1724160028,\"codec\":\"H265\"},{\"format\":1600261,\"defn\":\"V540P\",\"profile\":\"MP4\",\"path\":\"api/v4/11110105/mms/id-11110105-6ke1n-lyyvis0oge08ab.16002611734761662.mp4\",\"url\":\"https://down-aka-sg.vod.susercontent.com/api/v4/11110105/mms/id-11110105-6ke1n-lyyvis0oge08ab.16002611734761662.mp4\",\"width\":540,\"height\":960,\"bitrate\":363892,\"abitrate\":32382,\"duration\":17040,\"size\":858999,\"fps\":25,\"update_time\":1734761680,\"codec\":\"H265\"},{\"format\":1600309,\"defn\":\"V720P\",\"profile\":\"MP4\",\"path\":\"api/v4/11110105/mms/id-11110105-6ke1n-lyyvis0oge08ab.16003091723711024.mp4\",\"url\":\"https://down-aka-sg.vod.susercontent.com/api/v4/11110105/mms/id-11110105-6ke1n-lyyvis0oge08ab.16003091723711024.mp4\",\"width\":720,\"height\":1280,\"bitrate\":717377,\"abitrate\":127319,\"duration\":17020,\"size\":1813709,\"fps\":25.05882,\"update_time\":1723711056,\"codec\":\"H265\"},{\"format\":1600317,\"defn\":\"V720P\",\"profile\":\"MP4\",\"path\":\"api/v4/11110105/mms/id-11110105-6ke1n-lyyvis0oge08ab.16003171724153945.mp4\",\"url\":\"https://down-aka-sg.vod.susercontent.com/api/v4/11110105/mms/id-11110105-6ke1n-lyyvis0oge08ab.16003171724153945.mp4\",\"width\":720,\"height\":1280,\"bitrate\":779160,\"abitrate\":127319,\"duration\":17020,\"size\":1944995,\"fps\":25.05882,\"update_time\":1724153976,\"codec\":\"H265\"},{\"format\":1600318,\"defn\":\"V720P\",\"profile\":\"MP4\",\"path\":\"api/v4/11110105/mms/id-11110105-6ke1n-lyyvis0oge08ab.16003181724153945.mp4\",\"url\":\"https://down-aka-sg.vod.susercontent.com/api/v4/11110105/mms/id-11110105-6ke1n-lyyvis0oge08ab.16003181724153945.mp4\",\"width\":720,\"height\":1280,\"bitrate\":840699,\"abitrate\":127319,\"duration\":17020,\"size\":2075767,\"fps\":25.05882,\"update_time\":1724153980,\"codec\":\"H265\"},{\"format\":1600414,\"defn\":\"V720P\",\"profile\":\"MP4\",\"path\":\"api/v4/11110105/mms/id-11110105-6ke1n-lyyvis0oge08ab.16004141724160007.mp4\",\"url\":\"https://down-aka-sg.vod.susercontent.com/api/v4/11110105/mms/id-11110105-6ke1n-lyyvis0oge08ab.16004141724160007.mp4\",\"width\":720,\"height\":1280,\"bitrate\":631013,\"abitrate\":127319,\"duration\":17020,\"size\":1630195,\"fps\":25.05882,\"update_time\":1724160043,\"codec\":\"H265\"},{\"format\":1600415,\"defn\":\"V720P\",\"profile\":\"MP4\",\"path\":\"api/v4/11110105/mms/id-11110105-6ke1n-lyyvis0oge08ab.16004151724160007.mp4\",\"url\":\"https://down-aka-sg.vod.susercontent.com/api/v4/11110105/mms/id-11110105-6ke1n-lyyvis0oge08ab.16004151724160007.mp4\",\"width\":720,\"height\":1280,\"bitrate\":842742,\"abitrate\":127319,\"duration\":17020,\"size\":2087071,\"fps\":30.05882,\"update_time\":1724160038,\"codec\":\"H265\"},{\"format\":1600260,\"defn\":\"V720P\",\"profile\":\"MP4\",\"path\":\"api/v4/11110105/mms/id-11110105-6ke1n-lyyvis0oge08ab.16002601734761662.mp4\",\"url\":\"https://down-aka-sg.vod.susercontent.com/api/v4/11110105/mms/id-11110105-6ke1n-lyyvis0oge08ab.16002601734761662.mp4\",\"width\":720,\"height\":1280,\"bitrate\":849581,\"abitrate\":48524,\"duration\":17033,\"size\":1932905,\"fps\":30.00059,\"update_time\":1734761681,\"codec\":\"H265\"},{\"format\":1600262,\"defn\":\"V720P\",\"profile\":\"MP4\",\"path\":\"api/v4/11110105/mms/id-11110105-6ke1n-lyyvis0oge08ab.16002621734761662.mp4\",\"url\":\"https://down-aka-sg.vod.susercontent.com/api/v4/11110105/mms/id-11110105-6ke1n-lyyvis0oge08ab.16002621734761662.mp4\",\"width\":720,\"height\":1280,\"bitrate\":849763,\"abitrate\":64699,\"duration\":17033,\"size\":1967658,\"fps\":30.00059,\"update_time\":1734761695,\"codec\":\"H265\"}]},\"default_format\":{\"format\":1600323,\"defn\":\"V540P\",\"profile\":\"MP4\",\"url\":\"https://mms.vod.susercontent.com/api/v4/11110105/mms/id-11110105-6ke1n-lyyvis0oge08ab.default.mp4\",\"width\":540,\"height\":960,\"bitrate\":490742,\"abitrate\":127373,\"duration\":17024,\"size\":1328160,\"fps\":25.05882,\"update_time\":1723711033,\"codec\":\"H264\"}}",
        "item_cover": null
      },
      "images": [
        "id-11134207-7rase-m59ofxfl4sjm44",
        "id-11134207-7rasd-m59ofxfl4shsf8",
        "id-11134207-7rasc-m59ofxfl4serf0",
        "id-11134207-7rasc-m59ofxfl4sd4dd",
        "id-11134207-7r98x-llpy2wp5ps0v73"
      ],
      "first_tier_variations": [
        {
          "name": "80/90-14",
          "image": "id-11134207-7rasl-m59ofxfl66xkad",
          "summed_stock": 19318,
          "display_indicator": 0
        },
        {
          "name": "90/90-14",
          "image": "id-11134207-7rasf-m59ofxfl7li048",
          "summed_stock": 3066,
          "display_indicator": 0
        },
        {
          "name": "Satu Set Matic",
          "image": "id-11134207-7rash-m59ofxfl902gca",
          "summed_stock": 32,
          "display_indicator": 0
        }
      ],
      "sorted_variation_image_index_list": [
        0,
        1,
        2
      ],
      "overlay": null,
      "makeup_preview": null,
      "abnormal_status": "",
      "promotion_images": [],
      "long_images": null,
      "shopee_video_info_list": [],
      "shopee_video_rcmd_info": null,
      "shopee_video_req_id": null,
      "skincam": null,
      "pdp_top_info_list": null,
      "has_long_image": null
    },
    "product_price": {
      "discount": 50,
      "installment_info": null,
      "spl_installment_info": null,
      "pack_size": "",
      "hide_price": false,
      "price": {
        "single_value": -1,
        "range_min": 8928600000,
        "range_max": 26785700000,
        "price_mask": null
      },
      "price_before_discount": {
        "single_value": -1,
        "range_min": 17857100000,
        "range_max": 53571400000,
        "price_mask": null
      },
      "presale_price": null,
      "lowest_past_price": null,
      "labels": [
        {
          "type": 0,
          "text": "Bebas Pengembalian",
          "color": "#26AA99",
          "display": "free_return",
          "exclusive_price": null,
          "promotion_id": null
        }
      ],
      "hide_discount": false,
      "discount_text": "-50%",
      "show_final_price_indicator": false,
      "final_price_vouchers": null
    },
    "flash_sale": null,
    "flash_sale_preview": null,
    "deep_discount": null,
    "exclusive_price": null,
    "exclusive_price_cta": null,
    "product_meta": {
      "show_lowest_price_guarantee": null,
      "show_original_guarantee": null,
      "show_best_price_guarantee": false,
      "show_official_shop_label_in_title": true,
      "show_shopee_verified_label": false,
      "show_lowest_installment_guarantee": null,
      "hide_sharing_button": false,
      "hide_sold_count": false
    },
    "product_review": {
      "rating_star": 4.577985323549033,
      "rating_count": [
        7502,
        258,
        138,
        294,
        1129,
        5683
      ],
      "total_rating_count": 7502,
      "historical_sold": 15816,
      "global_sold": 15816,
      "liked": false,
      "liked_count": 4409,
      "cmt_count": 7203,
      "should_move_ratings_above": null,
      "review_rcmd_exp_group": null,
      "display_global_sold": false,
      "hide_rating": false,
      "hide_buyer_gallery": false,
      "hide_reviews": false,
      "hide_other_product_reviews_in_shop": false
    },
    "promotion_info": {
      "spl": null,
      "spl_lite": null,
      "installment": null,
      "wholesale": null,
      "insurance": null,
      "item_installment_eligibility": {
        "is_cc_installment_payment_eligible": false,
        "is_non_cc_installment_payment_eligible": false
      }
    },
    "age_gate": {
      "kyc": null
    },
    "shipping_meta": {
      "show_fufilled_by_shopee": false,
      "show_cod": true,
      "show_mart": false,
      "show_next_day_delivery": false
    },
    "product_shipping": {
      "free_shipping": {
        "min_spend": {
          "single_value": 2000000000,
          "range_min": -1,
          "range_max": -1,
          "price_mask": null
        },
        "has_fss": true
      },
      "shipping_fee_info": {
        "ship_from_location": "KAB. BANYUWANGI",
        "price": {
          "single_value": -1,
          "range_min": 0,
          "range_max": 3000000000,
          "price_mask": null
        },
        "shipping_icon_type": 0,
        "warning": null
      },
      "show_shipping_to": true,
      "ungrouped_channel_infos": [
        {
          "channel_id": 8003,
          "name": "Reguler",
          "price": {
            "single_value": 0,
            "range_min": -1,
            "range_max": -1,
            "price_mask": null
          },
          "price_before_discount": {
            "single_value": 5100000000,
            "range_min": -1,
            "range_max": -1,
            "price_mask": null
          },
          "channel_delivery_info": {
            "has_edt": true,
            "display_mode": "edt_by_date",
            "estimated_delivery_date_from": 1739469864,
            "estimated_delivery_date_to": 1739683108,
            "estimated_delivery_time_min": 4,
            "estimated_delivery_time_max": 6,
            "delay_message": null,
            "is_fastest_edt_channel": false,
            "sla_message": "",
            "show_edt": true,
            "edt_text": "Garansi tiba: 14 - 16 Februari",
            "formatted_edt_text": [
              {
                "template": "Garansi tiba: 14 - 16 Februari",
                "format": null,
                "attributes": null,
                "text_color": null,
                "text_hex_color": null
              }
            ]
          },
          "channel_promotion_infos": [],
          "warning": null,
          "shipping_icon_type": null,
          "lowest_bpsf_promotion_rule": null,
          "service_type_info": "regular",
          "is_integrated_channel": true,
          "late_delivery_compensation": {
            "type": 1,
            "amount": 1000000000,
            "is_guaranteed_edt": true,
            "compensation_amount": null,
            "text": null
          },
          "is_sst_included": false,
          "display_text": {
            "late_delivery_compensation": null,
            "direct_delivery": null,
            "fulfilled_by_shopee": null,
            "spx_instant_delivery": null
          },
          "rule_type": 0,
          "is_xdd_channel": false,
          "show_shopee_plus_icon": false,
          "xdd_value": null
        },
        {
          "channel_id": 8005,
          "name": "Hemat",
          "price": {
            "single_value": 0,
            "range_min": -1,
            "range_max": -1,
            "price_mask": null
          },
          "price_before_discount": {
            "single_value": 4800000000,
            "range_min": -1,
            "range_max": -1,
            "price_mask": null
          },
          "channel_delivery_info": {
            "has_edt": true,
            "display_mode": "edt_by_date",
            "estimated_delivery_date_from": 1739476379,
            "estimated_delivery_date_to": 1739685113,
            "estimated_delivery_time_min": 4,
            "estimated_delivery_time_max": 6,
            "delay_message": null,
            "is_fastest_edt_channel": false,
            "sla_message": "",
            "show_edt": true,
            "edt_text": "Garansi tiba: 14 - 16 Februari",
            "formatted_edt_text": [
              {
                "template": "Garansi tiba: 14 - 16 Februari",
                "format": null,
                "attributes": null,
                "text_color": null,
                "text_hex_color": null
              }
            ]
          },
          "channel_promotion_infos": [],
          "warning": null,
          "shipping_icon_type": null,
          "lowest_bpsf_promotion_rule": null,
          "service_type_info": "regular",
          "is_integrated_channel": true,
          "late_delivery_compensation": {
            "type": 1,
            "amount": 1000000000,
            "is_guaranteed_edt": true,
            "compensation_amount": null,
            "text": null
          },
          "is_sst_included": false,
          "display_text": {
            "late_delivery_compensation": null,
            "direct_delivery": null,
            "fulfilled_by_shopee": null,
            "spx_instant_delivery": null
          },
          "rule_type": 0,
          "is_xdd_channel": false,
          "show_shopee_plus_icon": false,
          "xdd_value": null
        },
        {
          "channel_id": 8006,
          "name": "Kargo",
          "price": {
            "single_value": -1,
            "range_min": 0,
            "range_max": 3000000000,
            "price_mask": null
          },
          "price_before_discount": null,
          "channel_delivery_info": {
            "has_edt": true,
            "display_mode": "edt_by_date",
            "estimated_delivery_date_from": 1739405600,
            "estimated_delivery_date_to": 1739523087,
            "estimated_delivery_time_min": 3,
            "estimated_delivery_time_max": 4,
            "delay_message": null,
            "is_fastest_edt_channel": true,
            "sla_message": "",
            "show_edt": true,
            "edt_text": "Diperkirakan diterima: 13 sampai 14 Februari",
            "formatted_edt_text": [
              {
                "template": "Diperkirakan diterima: 13 sampai 14 Februari",
                "format": [
                  2
                ],
                "attributes": null,
                "text_color": null,
                "text_hex_color": "#26AA99"
              }
            ]
          },
          "channel_promotion_infos": [
            {
              "rule_id": 264114312314881,
              "type": 1,
              "display_mode": null,
              "discount_off": null,
              "min_spend": {
                "single_value": 10000000000,
                "range_min": -1,
                "range_max": -1,
                "price_mask": null
              },
              "cap": null
            }
          ],
          "warning": null,
          "shipping_icon_type": null,
          "lowest_bpsf_promotion_rule": null,
          "service_type_info": "regular_cargo",
          "is_integrated_channel": true,
          "late_delivery_compensation": null,
          "is_sst_included": false,
          "display_text": {
            "late_delivery_compensation": null,
            "direct_delivery": null,
            "fulfilled_by_shopee": null,
            "spx_instant_delivery": null
          },
          "rule_type": 0,
          "is_xdd_channel": false,
          "show_shopee_plus_icon": false,
          "xdd_value": null
        },
        {
          "channel_id": 8000,
          "name": "Instant",
          "price": {
            "single_value": 0,
            "range_min": -1,
            "range_max": -1,
            "price_mask": null
          },
          "price_before_discount": null,
          "channel_delivery_info": {
            "has_edt": false,
            "display_mode": null,
            "estimated_delivery_date_from": null,
            "estimated_delivery_date_to": null,
            "estimated_delivery_time_min": null,
            "estimated_delivery_time_max": null,
            "delay_message": null,
            "is_fastest_edt_channel": false,
            "sla_message": "",
            "show_edt": null,
            "edt_text": null,
            "formatted_edt_text": null
          },
          "channel_promotion_infos": null,
          "warning": {
            "type": "unsupported_address",
            "warning_msg": "Layanan Tidak Tersedia"
          },
          "shipping_icon_type": null,
          "lowest_bpsf_promotion_rule": null,
          "service_type_info": "instant",
          "is_integrated_channel": true,
          "late_delivery_compensation": null,
          "is_sst_included": false,
          "display_text": {
            "late_delivery_compensation": null,
            "direct_delivery": null,
            "fulfilled_by_shopee": null,
            "spx_instant_delivery": null
          },
          "rule_type": 0,
          "is_xdd_channel": false,
          "show_shopee_plus_icon": false,
          "xdd_value": null
        }
      ],
      "grouped_channel_infos_by_service_type": [],
      "also_available_channel_name": null,
      "pre_selected_shipping_channel": null,
      "show_grouped_channel_first": null,
      "is_item_with_price_range": true,
      "also_available_channel_icon_type": null,
      "pre_order_text": "",
      "selected_late_delivery_compensation_for_drawer": {
        "type": 1,
        "amount": null,
        "is_guaranteed_edt": true,
        "compensation_amount": {
          "value": 1000000000
        },
        "text": "Dapatkan Voucher s/d {compensation_amount} jika pesanan terlambat."
      },
      "shipping_info_text": {
        "text_template": null,
        "shipping_fee": null,
        "edt_from": null,
        "edt_to": null,
        "show_shipping_fee_suffix": false,
        "formatted_text": null
      }
    },
    "shop_vouchers": [],
    "free_return": null,
    "coin_info": {
      "spend_cash_unit": 100000,
      "coin_earn_items": [
        {
          "coin_earn": 0
        },
        {
          "coin_earn": 0
        },
        {
          "coin_earn": 0
        },
        {
          "coin_earn": 0
        },
        {
          "coin_earn": 0
        },
        {
          "coin_earn": 0
        },
        {
          "coin_earn": 0
        },
        {
          "coin_earn": 0
        },
        {
          "coin_earn": 0
        }
      ],
      "coin_earn_label": null
    },
    "product_attributes": {
      "attrs": [
        {
          "name": "Stok",
          "value": "22416",
          "id": null,
          "is_timestamp": null,
          "brand_option": null,
          "val_id": null,
          "url": null,
          "brand_id": null,
          "full_url": null,
          "type": 7
        },
        {
          "name": "Merek",
          "value": "Erco",
          "id": null,
          "is_timestamp": null,
          "brand_option": null,
          "val_id": null,
          "url": "/search?brands=1957770",
          "brand_id": 1957770,
          "full_url": "https://shopee.co.id/search?brands=1957770",
          "type": 1
        },
        {
          "name": "Bahan",
          "value": "Alloy, Double Nylon",
          "id": 100134,
          "is_timestamp": null,
          "brand_option": null,
          "val_id": null,
          "url": null,
          "brand_id": null,
          "full_url": null,
          "type": 5
        },
        {
          "name": "Set Bundle",
          "value": "Ya",
          "id": 100391,
          "is_timestamp": null,
          "brand_option": null,
          "val_id": null,
          "url": null,
          "brand_id": null,
          "full_url": null,
          "type": 5
        },
        {
          "name": "Jenis Ban",
          "value": "Performance Semua Musim",
          "id": 100880,
          "is_timestamp": null,
          "brand_option": null,
          "val_id": null,
          "url": null,
          "brand_id": null,
          "full_url": null,
          "type": 5
        },
        {
          "name": "Masa Garansi",
          "value": "1 Bulan",
          "id": 100121,
          "is_timestamp": null,
          "brand_option": null,
          "val_id": null,
          "url": null,
          "brand_id": null,
          "full_url": null,
          "type": 5
        },
        {
          "name": "Jenis Garansi",
          "value": "Garansi Produsen",
          "id": 100370,
          "is_timestamp": null,
          "brand_option": null,
          "val_id": null,
          "url": null,
          "brand_id": null,
          "full_url": null,
          "type": 5
        },
        {
          "name": "Ukuran Ban Sepeda Motor",
          "value": "90/90-14",
          "id": 100917,
          "is_timestamp": null,
          "brand_option": null,
          "val_id": null,
          "url": null,
          "brand_id": null,
          "full_url": null,
          "type": 5
        },
        {
          "name": "No.Sertifikat (SNI,K3L,UTTP)",
          "value": "31052200380910001",
          "id": 101256,
          "is_timestamp": null,
          "brand_option": null,
          "val_id": null,
          "url": null,
          "brand_id": null,
          "full_url": null,
          "type": 5
        },
        {
          "name": "Dikirim Dari",
          "value": "KAB. BANYUWANGI",
          "id": null,
          "is_timestamp": null,
          "brand_option": null,
          "val_id": null,
          "url": null,
          "brand_id": null,
          "full_url": null,
          "type": 6
        }
      ],
      "categories": [
        {
          "catid": 11043660,
          "display_name": "Otomotif",
          "no_sub": false,
          "is_default_subcat": false
        },
        {
          "catid": 11043747,
          "display_name": "Suku Cadang Motor",
          "no_sub": false,
          "is_default_subcat": false
        },
        {
          "catid": 11043767,
          "display_name": "Ban Motor & Aksesoris",
          "no_sub": true,
          "is_default_subcat": false
        }
      ],
      "related_items": []
    },
    "shop_detailed": {
      "shopid": 158804442,
      "userid": 158806464,
      "last_active_time": 1739182046,
      "vacation": false,
      "place": "KAB. BANYUWANGI - TEGALDLIMO, JAWA TIMUR, ID",
      "account": {
        "portrait": "sg-11134004-7qvfh-ligxywapismn4f",
        "username": "ercotire",
        "status": 1
      },
      "is_shopee_verified": false,
      "is_preferred_plus_seller": false,
      "is_official_shop": true,
      "shop_location": "KAB. BANYUWANGI",
      "item_count": 30,
      "rating_star": 4.58757,
      "response_rate": 87,
      "session_info": {
        "is_show": true,
        "session_id": 117589636,
        "view_count": 0,
        "session_url": "https://play-bs-src.livestream.shopee.co.id/live/id-live-3324277776748032-117589636_spexsd.flv?auditkey=1.0~9SzTwSf5j7Y18OkO3y2jNJuulxExTpI5tCUQnXHkaPIa9VtKKu8rJdAD97Pgok4lWTkRx0umPBrCBI1JTZaCQCms47bz2pMWKERX_HGk_Kc~6a9f0d38bbe0470b39536259bf047ff246de57c9c455100845619a0b06fffdb5&cdnID=BAISHAN&expire_ts=1739184033&tcLevel=new_user%2Creturning%2Cnormal",
        "preview_image": "id-11134104-7rasl-m619oizcusd2e7",
        "streamer_user_id": 1468300437,
        "streamer_shop_id": 1467530634,
        "recommendation_info": "QUE:STREAM-FLOAT-WINDOW-Item2Stream,QUES:STREAM-FLOAT-WINDOW-Item2Stream,QLVS:2,RNK:DAGlivestream-PdpModelUniRank:{SCORE:0.000026950829555292912},REQID:b11ba3af2dc6eb38a235c101f119d702,RNKMOD:ctr=0.009447028860449791|cvr=0.0028515346348285675,EXTRA:RULES@155-598|72-347|249-1372|249-1331##CHAN@RCMD,SCENE:livestream_pdp,UAF:0,CHAN:RCMD,STIME:1739182233575,HOSTID:1468300437,BND:livestream_pdp,ABTEST:0.a.000@314798",
        "ads_info": null,
        "track_id": "recommendation_info=QUE:STREAM-FLOAT-WINDOW-Item2Stream,QUES:STREAM-FLOAT-WINDOW-Item2Stream,QLVS:2,RNK:DAGlivestream-PdpModelUniRank:{SCORE:0.000026950829555292912},REQID:b11ba3af2dc6eb38a235c101f119d702,RNKMOD:ctr=0.009447028860449791|cvr=0.0028515346348285675,EXTRA:RULES@155-598|72-347|249-1372|249-1331##CHAN@RCMD,SCENE:livestream_pdp,UAF:0,CHAN:RCMD,STIME:1739182233575,HOSTID:1468300437,BND:livestream_pdp,ABTEST:0.a.000@314798"
      },
      "name": "Erco Tire Official Store",
      "ctime": 1561778531,
      "response_time": 10425,
      "follower_count": 21716,
      "show_official_shop_label": true,
      "rating_bad": 448,
      "rating_good": 13363,
      "rating_normal": 828,
      "session_infos": [
        {
          "is_show": true,
          "session_id": 117589636,
          "view_count": 0,
          "session_url": "https://play-bs-src.livestream.shopee.co.id/live/id-live-3324277776748032-117589636_spexsd.flv?auditkey=1.0~9SzTwSf5j7Y18OkO3y2jNJuulxExTpI5tCUQnXHkaPIa9VtKKu8rJdAD97Pgok4lWTkRx0umPBrCBI1JTZaCQCms47bz2pMWKERX_HGk_Kc~6a9f0d38bbe0470b39536259bf047ff246de57c9c455100845619a0b06fffdb5&cdnID=BAISHAN&expire_ts=1739184033&tcLevel=new_user%2Creturning%2Cnormal",
          "preview_image": "id-11134104-7rasl-m619oizcusd2e7",
          "streamer_user_id": 1468300437,
          "streamer_shop_id": 1467530634,
          "recommendation_info": "QUE:STREAM-FLOAT-WINDOW-Item2Stream,QUES:STREAM-FLOAT-WINDOW-Item2Stream,QLVS:2,RNK:DAGlivestream-PdpModelUniRank:{SCORE:0.000026950829555292912},REQID:b11ba3af2dc6eb38a235c101f119d702,RNKMOD:ctr=0.009447028860449791|cvr=0.0028515346348285675,EXTRA:RULES@155-598|72-347|249-1372|249-1331##CHAN@RCMD,SCENE:livestream_pdp,UAF:0,CHAN:RCMD,STIME:1739182233575,HOSTID:1468300437,BND:livestream_pdp,ABTEST:0.a.000@314798",
          "ads_info": null,
          "track_id": "recommendation_info=QUE:STREAM-FLOAT-WINDOW-Item2Stream,QUES:STREAM-FLOAT-WINDOW-Item2Stream,QLVS:2,RNK:DAGlivestream-PdpModelUniRank:{SCORE:0.000026950829555292912},REQID:b11ba3af2dc6eb38a235c101f119d702,RNKMOD:ctr=0.009447028860449791|cvr=0.0028515346348285675,EXTRA:RULES@155-598|72-347|249-1372|249-1331##CHAN@RCMD,SCENE:livestream_pdp,UAF:0,CHAN:RCMD,STIME:1739182233575,HOSTID:1468300437,BND:livestream_pdp,ABTEST:0.a.000@314798"
        },
        {
          "is_show": true,
          "session_id": 117625576,
          "view_count": 2,
          "session_url": "https://play-ws-src.livestream.shopee.co.id/livestreaming/id-live-2796437197996544-117625576_spexsd.flv?auditkey=1.0~Ksg9Ba5e6UWOnzBYH-uQvHZdOYA86OqLvdOjmR3KLHrB9hXU1dMkz0T38FMHRu-YXtxDteQVMXoFl4o270A4RjJzpJzPqOTkLBaNFdIWE1k~e4e042393aa9fd974bd209dd8b6055f9339cfe43e4bdbfd45ceef3fac61775f5&cdnID=WANGSU&expire_ts=1739184033&tcLevel=rank_54386%2Clow",
          "preview_image": "id-11134104-7r98o-lsprc8bfxqwt11",
          "streamer_user_id": 1175257660,
          "streamer_shop_id": 1174911922,
          "recommendation_info": "QUE:STREAM-FLOAT-WINDOW-Item2Stream,QUES:STREAM-FLOAT-WINDOW-Item2Stream,QLVS:2,RNK:DAGlivestream-PdpModelUniRank:{SCORE:0.000018728829292945158},REQID:b11ba3af2dc6eb38a235c101f119d702,RNKMOD:ctr=0.007315447553992271|cvr=0.0025588255375623703,EXTRA:RULES@155-598|72-347|249-1372|249-1331##CHAN@RCMD,SCENE:livestream_pdp,UAF:0,CHAN:RCMD,STIME:1739182233575,HOSTID:1175257660,BND:livestream_pdp,ABTEST:0.a.000@314798",
          "ads_info": null,
          "track_id": "recommendation_info=QUE:STREAM-FLOAT-WINDOW-Item2Stream,QUES:STREAM-FLOAT-WINDOW-Item2Stream,QLVS:2,RNK:DAGlivestream-PdpModelUniRank:{SCORE:0.000018728829292945158},REQID:b11ba3af2dc6eb38a235c101f119d702,RNKMOD:ctr=0.007315447553992271|cvr=0.0025588255375623703,EXTRA:RULES@155-598|72-347|249-1372|249-1331##CHAN@RCMD,SCENE:livestream_pdp,UAF:0,CHAN:RCMD,STIME:1739182233575,HOSTID:1175257660,BND:livestream_pdp,ABTEST:0.a.000@314798"
        },
        {
          "is_show": true,
          "session_id": 117618063,
          "view_count": 26,
          "session_url": "https://play-spe.livestream.shopee.co.id/live/id-live-2789487949956096-117618063_spexsd.flv?auditkey=1.0~3H7TdUmk71CcWRnl4h5rGH39e7skVu8TuAf2FEcJED7qTD2-laUgHTBhoQD7xmfeB7lmpfMRqoaw76TLky8xvEBxhLIuP9K0pafWi-De-Ns~a6aa647d3727233873aa7195b026957f49b98278c702e4a60286410896afe232&cdnID=SHOPEE&expire_ts=1739184033&tcLevel=1080P%2Crank_5447%2Cnormal",
          "preview_image": "id-11134104-7r98o-lria2cr9w0ndea",
          "streamer_user_id": 1171744779,
          "streamer_shop_id": 1171405181,
          "recommendation_info": "QUE:STREAM-FLOAT-WINDOW-Item2Stream,QUES:STREAM-FLOAT-WINDOW-Item2Stream,QLVS:2,RNK:DAGlivestream-PdpModelUniRank:{SCORE:0.000013681709298838319},REQID:b11ba3af2dc6eb38a235c101f119d702,RNKMOD:ctr=0.009273693896830082|cvr=0.00147416559047997,EXTRA:RULES@155-598|72-347|249-1372|249-1331##CHAN@RCMD,SCENE:livestream_pdp,UAF:0,CHAN:RCMD,STIME:1739182233575,HOSTID:1171744779,BND:livestream_pdp,ABTEST:0.a.000@314798",
          "ads_info": null,
          "track_id": "recommendation_info=QUE:STREAM-FLOAT-WINDOW-Item2Stream,QUES:STREAM-FLOAT-WINDOW-Item2Stream,QLVS:2,RNK:DAGlivestream-PdpModelUniRank:{SCORE:0.000013681709298838319},REQID:b11ba3af2dc6eb38a235c101f119d702,RNKMOD:ctr=0.009273693896830082|cvr=0.00147416559047997,EXTRA:RULES@155-598|72-347|249-1372|249-1331##CHAN@RCMD,SCENE:livestream_pdp,UAF:0,CHAN:RCMD,STIME:1739182233575,HOSTID:1171744779,BND:livestream_pdp,ABTEST:0.a.000@314798"
        },
        {
          "is_show": true,
          "session_id": 117618671,
          "view_count": 1,
          "session_url": "https://play-bs-src.livestream.shopee.co.id/live/id-live-1333748263239680-117618671_spexsd.flv?auditkey=1.0~ehG2QHKay7sAuoklyCU2BZXfh54ApUitTnIQolNe8dsG191GWjI0kW7qI9-_vv4g87OdSrmQTe_yF9rwiImBBQO8ohIfAm_FAKL0hvy0Pwg~850aa866c68480c4e2347d7c55f3b9e288e17c833abdbcc6c058d79c7b2e09e1&cdnID=BAISHAN&expire_ts=1739184033&tcLevel=rank_75363%2Clow",
          "preview_image": "id-11134104-7rase-m2t4mrziv068d8",
          "streamer_user_id": 413958244,
          "streamer_shop_id": 413938667,
          "recommendation_info": "QUE:STREAM-FLOAT-WINDOW-Item2Stream,QUES:STREAM-FLOAT-WINDOW-Item2Stream,QLVS:2,RNK:DAGlivestream-PdpModelUniRank:{SCORE:0.000008705358973449023},REQID:b11ba3af2dc6eb38a235c101f119d702,RNKMOD:ctr=0.006883992813527584|cvr=0.0012633962323889136,EXTRA:RULES@155-598|72-347|249-1372|249-1331##CHAN@RCMD,SCENE:livestream_pdp,UAF:0,CHAN:RCMD,STIME:1739182233575,HOSTID:413958244,BND:livestream_pdp,ABTEST:0.a.000@314798",
          "ads_info": null,
          "track_id": "recommendation_info=QUE:STREAM-FLOAT-WINDOW-Item2Stream,QUES:STREAM-FLOAT-WINDOW-Item2Stream,QLVS:2,RNK:DAGlivestream-PdpModelUniRank:{SCORE:0.000008705358973449023},REQID:b11ba3af2dc6eb38a235c101f119d702,RNKMOD:ctr=0.006883992813527584|cvr=0.0012633962323889136,EXTRA:RULES@155-598|72-347|249-1372|249-1331##CHAN@RCMD,SCENE:livestream_pdp,UAF:0,CHAN:RCMD,STIME:1739182233575,HOSTID:413958244,BND:livestream_pdp,ABTEST:0.a.000@314798"
        },
        {
          "is_show": true,
          "session_id": 117618442,
          "view_count": 1,
          "session_url": "https://play-tx-src.livestream.shopee.co.id/live/id-live-3254662413916672-117618442_spexsd.flv?auditkey=1.0~OTi1hlMxQyHKmsxsivIZuUA6feKCIHRhZA1-_32k7LIlQCbvFGZczXbO-M0bWWnRnap8KLjECNMajP-2owtq5UncLsO5P5F0BQkxpT0nrvA~04a5cf2445b8d5d0dbb9751d57d3974f6b4628fd5f46e026dc7b27ecbdc10201&cdnID=TXCLOUD&expire_ts=1739184033&tcLevel=rank_82979%2Clow",
          "preview_image": "id-11134104-7rase-m3vlvs3ty8en66",
          "streamer_user_id": 1430892518,
          "streamer_shop_id": 1430187915,
          "recommendation_info": "QUE:STREAM-FLOAT-WINDOW-Item2Stream,QUES:STREAM-FLOAT-WINDOW-Item2Stream,QLVS:2,RNK:DAGlivestream-PdpModelUniRank:{SCORE:0.000007605933356705215},REQID:b11ba3af2dc6eb38a235c101f119d702,RNKMOD:ctr=0.008799643255770206|cvr=0.0008632474346086383,EXTRA:RULES@155-598|72-347|249-1372|249-1331##CHAN@RCMD,SCENE:livestream_pdp,UAF:0,CHAN:RCMD,STIME:1739182233575,HOSTID:1430892518,BND:livestream_pdp,ABTEST:0.a.000@314798",
          "ads_info": null,
          "track_id": "recommendation_info=QUE:STREAM-FLOAT-WINDOW-Item2Stream,QUES:STREAM-FLOAT-WINDOW-Item2Stream,QLVS:2,RNK:DAGlivestream-PdpModelUniRank:{SCORE:0.000007605933356705215},REQID:b11ba3af2dc6eb38a235c101f119d702,RNKMOD:ctr=0.008799643255770206|cvr=0.0008632474346086383,EXTRA:RULES@155-598|72-347|249-1372|249-1331##CHAN@RCMD,SCENE:livestream_pdp,UAF:0,CHAN:RCMD,STIME:1739182233575,HOSTID:1430892518,BND:livestream_pdp,ABTEST:0.a.000@314798"
        },
        {
          "is_show": true,
          "session_id": 117552508,
          "view_count": 4,
          "session_url": "https://play-hw-src.livestream.shopee.co.id/live/id-live-816839938871343-117552508_spexsd.flv?auditkey=1.0~zPb4kN2SrG0fhmWpUHnAC2EKdss416Y9gpgd3VbVKdDe8iMRh9eRUTe_h52pQgEKfx7H14dOexSymh15PH6FxSIQdzjIyYjnOiVgrz1qDuU~3876077c411253af73cf22a4dc7d52fcbe8f0d27d0a22367a678cc326ed5d200&cdnID=HUAWEI&expire_ts=1739184033&tcLevel=1080P%2Crank_3590%2Cnormal",
          "preview_image": "id-11134104-7rasm-m5t9qi0s5cbc71",
          "streamer_user_id": 111488062,
          "streamer_shop_id": 111486472,
          "recommendation_info": "QUE:STREAM-FLOAT-WINDOW-Item2Stream,QUES:STREAM-FLOAT-WINDOW-Item2Stream,QLVS:2,RNK:DAGlivestream-PdpModelUniRank:{SCORE:0.0000073332157455962945},REQID:b11ba3af2dc6eb38a235c101f119d702,RNKMOD:ctr=0.007768383249640465|cvr=0.0009428607299923897,EXTRA:RULES@155-598|72-347|249-1372|249-1331##CHAN@RCMD,SCENE:livestream_pdp,UAF:0,CHAN:RCMD,STIME:1739182233575,HOSTID:111488062,BND:livestream_pdp,ABTEST:0.a.000@314798",
          "ads_info": null,
          "track_id": "recommendation_info=QUE:STREAM-FLOAT-WINDOW-Item2Stream,QUES:STREAM-FLOAT-WINDOW-Item2Stream,QLVS:2,RNK:DAGlivestream-PdpModelUniRank:{SCORE:0.0000073332157455962945},REQID:b11ba3af2dc6eb38a235c101f119d702,RNKMOD:ctr=0.007768383249640465|cvr=0.0009428607299923897,EXTRA:RULES@155-598|72-347|249-1372|249-1331##CHAN@RCMD,SCENE:livestream_pdp,UAF:0,CHAN:RCMD,STIME:1739182233575,HOSTID:111488062,BND:livestream_pdp,ABTEST:0.a.000@314798"
        },
        {
          "is_show": true,
          "session_id": 117612058,
          "view_count": 3,
          "session_url": "https://play-spe.livestream.shopee.co.id/live/id-live-1503697972235264-117612058_spexsd.flv?auditkey=1.0~Uf1b8BhSP1X5ng1_fAHgHYVncWUSxFGBd_6aiKdMgAjpZvwDIVVbR17SxifO3HyfK4YamZT1IL5pfnIBtr3nsdnSzP8VhKIJGsH9SAgxZD8~574e63d62ddb8334b22a6ace837df608467b56813c0b0b87492098fe1da0278d&cdnID=SHOPEE&expire_ts=1739184033&tcLevel=rank_2363%2Cnormal",
          "preview_image": "id-11134104-7r98p-louyfb1zkyml73",
          "streamer_user_id": 499447892,
          "streamer_shop_id": 499428314,
          "recommendation_info": "QUE:STREAM-FLOAT-WINDOW-Item2Stream,QUES:STREAM-FLOAT-WINDOW-Item2Stream,QLVS:2,RNK:DAGlivestream-PdpModelUniRank:{SCORE:0.000007060383747558561},REQID:b11ba3af2dc6eb38a235c101f119d702,RNKMOD:ctr=0.0065904464572668076|cvr=0.001070143305696547,EXTRA:RULES@155-598|72-347|249-1372|249-1331##CHAN@RCMD,SCENE:livestream_pdp,UAF:0,CHAN:RCMD,STIME:1739182233575,HOSTID:499447892,BND:livestream_pdp,ABTEST:0.a.000@314798",
          "ads_info": null,
          "track_id": "recommendation_info=QUE:STREAM-FLOAT-WINDOW-Item2Stream,QUES:STREAM-FLOAT-WINDOW-Item2Stream,QLVS:2,RNK:DAGlivestream-PdpModelUniRank:{SCORE:0.000007060383747558561},REQID:b11ba3af2dc6eb38a235c101f119d702,RNKMOD:ctr=0.0065904464572668076|cvr=0.001070143305696547,EXTRA:RULES@155-598|72-347|249-1372|249-1331##CHAN@RCMD,SCENE:livestream_pdp,UAF:0,CHAN:RCMD,STIME:1739182233575,HOSTID:499447892,BND:livestream_pdp,ABTEST:0.a.000@314798"
        },
        {
          "is_show": true,
          "session_id": 117634102,
          "view_count": 2,
          "session_url": "https://play-tx-src.livestream.shopee.co.id/live/id-live-3209807937426944-117634102_spexsd.flv?auditkey=1.0~xsCn-zyztl_YFcvAA5MpKzxHFq0AtqU_rm2j_eZ0-RFUaBCQlWkODpmzhcIwWMm00eNClhNBuW7Gokn-JkFsnJJN1kEQsNv0KBE8qLe_p1Q~f5924e4ca5a627d5a72a5c92b2066bb46583827a3a5fc7e39653b8329863222e&cdnID=TXCLOUD&expire_ts=1739184033&tcLevel=rank_45775%2Cnormal",
          "preview_image": "id-11134104-7rasg-m2rf1ak3ka1h24",
          "streamer_user_id": 1406028056,
          "streamer_shop_id": 1405268756,
          "recommendation_info": "QUE:STREAM-FLOAT-WINDOW-Item2Stream,QUES:STREAM-FLOAT-WINDOW-Item2Stream,QLVS:2,RNK:DAGlivestream-PdpModelUniRank:{SCORE:0.000007053081825773028},REQID:b11ba3af2dc6eb38a235c101f119d702,RNKMOD:ctr=0.005869079381227493|cvr=0.0012005309108644724,EXTRA:RULES@155-598|72-347|249-1372|249-1331##CHAN@RCMD,SCENE:livestream_pdp,UAF:0,CHAN:RCMD,STIME:1739182233575,HOSTID:1406028056,BND:livestream_pdp,ABTEST:0.a.000@314798",
          "ads_info": null,
          "track_id": "recommendation_info=QUE:STREAM-FLOAT-WINDOW-Item2Stream,QUES:STREAM-FLOAT-WINDOW-Item2Stream,QLVS:2,RNK:DAGlivestream-PdpModelUniRank:{SCORE:0.000007053081825773028},REQID:b11ba3af2dc6eb38a235c101f119d702,RNKMOD:ctr=0.005869079381227493|cvr=0.0012005309108644724,EXTRA:RULES@155-598|72-347|249-1372|249-1331##CHAN@RCMD,SCENE:livestream_pdp,UAF:0,CHAN:RCMD,STIME:1739182233575,HOSTID:1406028056,BND:livestream_pdp,ABTEST:0.a.000@314798"
        },
        {
          "is_show": true,
          "session_id": 117733863,
          "view_count": 1,
          "session_url": "https://play-hw-src.livestream.shopee.co.id/live/id-live-3279079660258816-117733863_spexsd.flv?auditkey=1.0~yVF5o421l3RgbavJikFJ7mrMRXxZs_bKQ26xC8nxw85UGadc-PZ5R4Lh4ImesvZ_C_jry7WjQt9xWkq2HjttBe3fEuL6S0_w1Rui0ft_MAQ~242f1b899e0f683a76e2284f057f723655b80615eb61ce2515f9cd568db638bd&cdnID=HUAWEI&expire_ts=1739184033&tcLevel=rank_127358%2Clow",
          "preview_image": "id-11134104-7rasj-m4mpq4ohikc488",
          "streamer_user_id": 1444033979,
          "streamer_shop_id": 1443283800,
          "recommendation_info": "QUE:STREAM-FLOAT-WINDOW-Item2Stream,QUES:STREAM-FLOAT-WINDOW-Item2Stream,QLVS:2,RNK:DAGlivestream-PdpModelUniRank:{SCORE:0.000006951621614584492},REQID:b11ba3af2dc6eb38a235c101f119d702,RNKMOD:ctr=0.007971062324941158|cvr=0.0008709979010745883,EXTRA:RULES@155-598|72-347|249-1372|249-1331##CHAN@RCMD,SCENE:livestream_pdp,UAF:0,CHAN:RCMD,STIME:1739182233575,HOSTID:1444033979,BND:livestream_pdp,ABTEST:0.a.000@314798",
          "ads_info": null,
          "track_id": "recommendation_info=QUE:STREAM-FLOAT-WINDOW-Item2Stream,QUES:STREAM-FLOAT-WINDOW-Item2Stream,QLVS:2,RNK:DAGlivestream-PdpModelUniRank:{SCORE:0.000006951621614584492},REQID:b11ba3af2dc6eb38a235c101f119d702,RNKMOD:ctr=0.007971062324941158|cvr=0.0008709979010745883,EXTRA:RULES@155-598|72-347|249-1372|249-1331##CHAN@RCMD,SCENE:livestream_pdp,UAF:0,CHAN:RCMD,STIME:1739182233575,HOSTID:1444033979,BND:livestream_pdp,ABTEST:0.a.000@314798"
        },
        {
          "is_show": true,
          "session_id": 117623686,
          "view_count": 5,
          "session_url": "https://play-hw-src.livestream.shopee.co.id/live/id-live-3279966561256448-117623686_spexsd.flv?auditkey=1.0~wwv8p1PM5Jwp5UMXgvhuZxUqkXinFF53SCTZxt2urmH9UNBu_1hqzitCEbRaq4i_6ZTvxJ2YaxNVFMxEdnflm-YKTAhhRluq8tfWeB9QRaE~1a09f494706c898bb5c8fc100cb9260978e685c6dfe601219cf729458640ada9&cdnID=HUAWEI&expire_ts=1739184033&tcLevel=rank_65358%2Clow",
          "preview_image": "id-11134104-7rasm-m4l4ch47l2uyaf",
          "streamer_user_id": 1444477993,
          "streamer_shop_id": 1443742863,
          "recommendation_info": "QUE:STREAM-FLOAT-WINDOW-Item2Stream,QUES:STREAM-FLOAT-WINDOW-Item2Stream,QLVS:2,RNK:DAGlivestream-PdpModelUniRank:{SCORE:0.0000063146786428453695},REQID:b11ba3af2dc6eb38a235c101f119d702,RNKMOD:ctr=0.009113448671996593|cvr=0.0006918206927366555,EXTRA:RULES@155-598|72-347|249-1372|249-1331##CHAN@RCMD,SCENE:livestream_pdp,UAF:0,CHAN:RCMD,STIME:1739182233575,HOSTID:1444477993,BND:livestream_pdp,ABTEST:0.a.000@314798",
          "ads_info": null,
          "track_id": "recommendation_info=QUE:STREAM-FLOAT-WINDOW-Item2Stream,QUES:STREAM-FLOAT-WINDOW-Item2Stream,QLVS:2,RNK:DAGlivestream-PdpModelUniRank:{SCORE:0.0000063146786428453695},REQID:b11ba3af2dc6eb38a235c101f119d702,RNKMOD:ctr=0.009113448671996593|cvr=0.0006918206927366555,EXTRA:RULES@155-598|72-347|249-1372|249-1331##CHAN@RCMD,SCENE:livestream_pdp,UAF:0,CHAN:RCMD,STIME:1739182233575,HOSTID:1444477993,BND:livestream_pdp,ABTEST:0.a.000@314798"
        }
      ],
      "status": 1,
      "is_individual_seller": null,
      "is_mart": false,
      "favorite_shop_info": null,
      "is_3pf": false,
      "sold_total": 36431,
      "is_shopee_choice": false,
      "is_high_end": false,
      "banner": {
        "shopee_choice": null
      },
      "authorized_brand": null,
      "is_scs": false
    },
    "age_gate_control": null,
    "abnormal_popup": null,
    "return_on_spot": null,
    "display_sections": {
      "add_on_deal": null,
      "bundle_deal": null,
      "exclusive_price_label": null,
      "free_return": null,
      "coin": null,
      "wholesale": null
    },
    "ineligible_ep": null,
    "tax_disclaimer": null,
    "alcohol_disclaimer": null,
    "design_control": {
      "use_new_revamp_first_screen": null,
      "display_on_time_delivery_guarantee": true,
      "disable_price_with_variation": false,
      "display_direct_delivery": false,
      "use_new_featured_video_revamp": null,
      "first_screen_revamp_abtest_group": null,
      "display_choice_customised_section": false,
      "is_support_fbs_enabled": false,
      "top_section_featured_video_ab_test_group": null,
      "enable_ksp_config": null
    },
    "shopee_free_return": null,
    "detail_level": 0,
    "removed_fields": null,
    "size_guide": null,
    "designer_info": null,
    "shipping_info": null,
    "vehicle_compatibility_info": null,
    "nea": null,
    "button_group": {
      "buy_with_voucher": null
    },
    "installment_drawer": {
      "priority": [
        0,
        1
      ],
      "spl": null,
      "bank": {
        "channels": null
      },
      "credit_card": null
    },
    "ongoing_banner": null,
    "teaser_banner": null,
    "price_breakdown": null,
    "membership_exclusive": null,
    "membership_exclusive_teaser": null,
    "service_entrance": {
      "services": [
        {
          "text": "15 Hari Pengembalian",
          "type": 1001,
          "id": 22
        },
        {
          "text": "100% Original",
          "type": 1,
          "id": 23
        },
        {
          "text": "Proteksi Kerusakan +",
          "type": 4,
          "id": 25
        }
      ]
    },
    "service_drawer": {
      "services": [
        {
          "title": "15 Hari Pengembalian",
          "description": "Untuk memastikan kepuasanmu, Shopee Mall memberikan periode pengembalian yang lebih panjang (15 hari setelah barang diterima).",
          "type": 1001,
          "free_return": null,
          "insurance": null,
          "id": 22,
          "redirection_url": "",
          "icon": "id-11134258-7rasm-m3bt65hlwhke96",
          "insurance_drawer": null
        },
        {
          "title": "100% Original",
          "description": "Produk ini dijamin 100% asli dan akan dikirimkan secara langsung. Jika produk yang diterima tidak asli, kamu dapat mengajukan Pengembalian Dana.",
          "type": 1,
          "free_return": null,
          "insurance": null,
          "id": 23,
          "redirection_url": "https://shopee.co.id/m/shopee-garansi-ori",
          "icon": "id-11134258-7ras8-m3bt6aa6vxsk65",
          "insurance_drawer": null
        },
        {
          "title": "Proteksi Kerusakan +",
          "description": "Melindungi barang belanjaanmu dari kerusakan total hingga 6 bulan",
          "type": 4,
          "free_return": null,
          "insurance": {
            "url": "https://insurance.shopee.co.id/ec/ec-pdp.html?from=pdp&locale=ID&product_id=1749285878540410882"
          },
          "id": 25,
          "redirection_url": "https://insurance.shopee.co.id/ec/ec-pdp.html?from=pdp&locale=ID&product_id=1749285878540410882",
          "icon": "id-11134258-7rasa-m3bt6nx0z2dw71",
          "insurance_drawer": {}
        }
      ]
    }
  }
}